INSTALL.html
INSTALL.txt
LICENSE.txt
MANIFEST.in
README.html
README.txt
ez_setup.py
metainfo.py
pdfgrid
pdfgrid.py
setup.cfg
setup.py
test_pdfgrid.py
test_pdfgridscript.py
pdfgrid.egg-info/PKG-INFO
pdfgrid.egg-info/SOURCES.txt
pdfgrid.egg-info/dependency_links.txt
pdfgrid.egg-info/top_level.txt
samples/.DS_Store
samples/genpdf.py
samples/test-a4-l-grid.pdf
samples/test-a4-l.pdf
samples/test-a4-p-grid-default.pdf
samples/test-a4-p-grid-origin.pdf
samples/test-a4-p-grid-style.pdf
samples/test-a4-p-grid-styles.pdf
samples/test-a4-p-grid.pdf
samples/test-a4-p.pdf