Metadata-Version: 1.0
Name: pdfgrid
Version: 0.2.0
Summary: Add a grid on top of all pages of a PDF document.
Home-page: http://www.dinu-gherman.net/
Author: Dinu Gherman
Author-email: gherman@darwin.in-berlin.de
License: GPL 3
Download-URL: http://www.dinu-gherman.net/tmp/pdfgrid-0.2.0.tar.gz
Keywords: overlay,grid,PDF
Platform: Posix
Platform: Windows
Classifier: Development Status :: 4 - Beta
Classifier: Environment :: Console
Classifier: Intended Audience :: End Users/Desktop
Classifier: Intended Audience :: Developers
Classifier: License :: OSI Approved :: GNU General Public License (GPL)
Classifier: Operating System :: MacOS :: MacOS X
Classifier: Operating System :: POSIX
Classifier: Operating System :: Microsoft :: Windows
Classifier: Natural Language :: English
Classifier: Programming Language :: Python
Classifier: Topic :: Utilities
Classifier: Topic :: Printing
